AUTHORS.md
CHANGELOG.md
CONTRIBUTING.md
LICENSE
MANIFEST.in
README.md
setup.cfg
setup.py
docs/Makefile
docs/conf.py
docs/make.bat
medicare_utils/__init__.py
medicare_utils/codebook.py
medicare_utils/codes.py
medicare_utils/medicare_df.py
medicare_utils/parquet.py
medicare_utils/utils.py
medicare_utils.egg-info/PKG-INFO
medicare_utils.egg-info/SOURCES.txt
medicare_utils.egg-info/dependency_links.txt
medicare_utils.egg-info/not-zip-safe
medicare_utils.egg-info/requires.txt
medicare_utils.egg-info/top_level.txt
medicare_utils/data/codebook/bsfab.json
medicare_utils/data/codebook/med.json
tests/__init__.py
tests/test_medicare_utils.py