Metadata-Version: 2.1
Name: medicare-utils
Version: 0.0.2
Summary: Scripts to assist working with Medicare data.
Home-page: https://github.com/kylebarron/medicare_utils
Author: Kyle Barron
Author-email: barronk@mit.edu
License: MIT license
Keywords: medicare_utils
Platform: UNKNOWN
Classifier: Development Status :: 2 - Pre-Alpha
Classifier: Intended Audience :: Developers
Classifier: License :: OSI Approved :: MIT License
Classifier: Natural Language :: English
Classifier: Programming Language :: Python :: 3
Classifier: Programming Language :: Python :: 3.4
Classifier: Programming Language :: Python :: 3.5
Classifier: Programming Language :: Python :: 3.6
